group_local/__init__.py
group_local/group_category.py
group_local/group_local_constants.py
group_local/group_type.py
group_local/groups_local.py
group_local-0.0.65.dist-info/METADATA
group_local-0.0.65.dist-info/WHEEL
group_local-0.0.65.dist-info/top_level.txt
group_local-0.0.65.dist-info/RECORD
