Metadata-Version: 2.4
Name: group-local
Version: 0.0.65
Summary: PyPI Package for Circles group-local Python
Home-page: https://github.com/circles-zone/group-main-local-python-package
Author: Circles
Author-email: info@circlez.ai
Classifier: Programming Language :: Python :: 3
Classifier: License :: Other/Proprietary License
Classifier: Operating System :: OS Independent
Requires-Dist: database_mysql_local>=0.0.333
Requires-Dist: logger_local>=0.0.145
Requires-Dist: language_remote>=0.0.22
Requires-Dist: user-context-remote>=0.0.84
Requires-Dist: job-local>=0.0.3
Dynamic: author
Dynamic: author-email
Dynamic: classifier
Dynamic: description
Dynamic: description-content-type
Dynamic: home-page
Dynamic: requires-dist
Dynamic: summary
